hantekpsu/__init__.py
hantekpsu/psu.py
hantekpsu-1.0.3.dist-info/METADATA
hantekpsu-1.0.3.dist-info/WHEEL
hantekpsu-1.0.3.dist-info/RECORD
