Metadata-Version: 2.1
Name: hantekpsu
Version: 1.0.3
Summary: Python interface for Hantek bench power supply
Home-page: https://github.com/builder555/hantek-controller
License: MIT-0
Author: builder555
Author-email: 85308587+builder555@users.noreply.github.com
Requires-Python: >=3.9,<4.0
Classifier: License :: OSI Approved
Classifier: Programming Language :: Python :: 3
Classifier: Programming Language :: Python :: 3.9
Classifier: Programming Language :: Python :: 3.10
Classifier: Programming Language :: Python :: 3.11
Classifier: Programming Language :: Python :: 3.12
Classifier: Programming Language :: Python :: 3.13
Requires-Dist: pyserial (>=3.5,<4.0)
Requires-Dist: pyserial-asyncio (>=0.6,<0.7)
